spectrophore/__init__.py
spectrophore/__main__.py
spectrophore/spectrophore.py
uamc_spectrophore-1.3.0.dist-info/LICENSE
uamc_spectrophore-1.3.0.dist-info/METADATA
uamc_spectrophore-1.3.0.dist-info/WHEEL
uamc_spectrophore-1.3.0.dist-info/entry_points.txt
uamc_spectrophore-1.3.0.dist-info/top_level.txt
uamc_spectrophore-1.3.0.dist-info/RECORD
