Metadata-Version: 2.1
Name: uamc-spectrophore
Version: 1.3.0
Summary: Python implementation of the spectrophore descriptor
Home-page: https://github.com/UAMCAntwerpen/spectrophore
Download-URL: https://github.com/silicos-it/spectrophore/releases/latest
Author: Hans De Winter
Author-email: hans.dewinter@uantwerpen.be
Keywords: uamc,spectrophore,rdkit,cheminformatics
Classifier: Development Status :: 5 - Production/Stable
Classifier: Environment :: Console
Classifier: Intended Audience :: Science/Research
Classifier: License :: Freeware
Classifier: Operating System :: POSIX :: Linux
Classifier: Operating System :: MacOS :: MacOS X
Classifier: Programming Language :: Python :: 3
Classifier: Topic :: Scientific/Engineering :: Chemistry
Classifier: Topic :: Software Development :: Libraries :: Python Modules
Requires-Python: >=3.9
License-File: LICENSE
Requires-Dist: numba
Requires-Dist: rdkit
Requires-Dist: scipy
Requires-Dist: numpy
Requires-Dist: tqdm
Provides-Extra: develop
Requires-Dist: pytest ; extra == 'develop'
Requires-Dist: pytest-cov ; extra == 'develop'
Requires-Dist: ruff ; extra == 'develop'
